bd_warehouse/__init__.py
bd_warehouse/_version.py
bd_warehouse/bearing.py
bd_warehouse/fastener.py
bd_warehouse/flange.py
bd_warehouse/gear.py
bd_warehouse/open_builds.py
bd_warehouse/pipe.csv
bd_warehouse/pipe.py
bd_warehouse/thread.py
bd_warehouse/data/brad_tee_nut_parameters.csv
bd_warehouse/data/button_head_parameters.csv
bd_warehouse/data/button_head_with_collar_parameters.csv
bd_warehouse/data/chamfered_washer_parameters.csv
bd_warehouse/data/cheese_head_parameters.csv
bd_warehouse/data/cheese_head_washer_parameters.csv
bd_warehouse/data/clearance_hole_sizes.csv
bd_warehouse/data/countersunk_head_parameters.csv
bd_warehouse/data/domed_cap_nut_parameters.csv
bd_warehouse/data/drill_sizes.csv
bd_warehouse/data/heatset_nut_parameters.csv
bd_warehouse/data/hex_head_parameters.csv
bd_warehouse/data/hex_head_with_flange_parameters.csv
bd_warehouse/data/hex_nut_parameters.csv
bd_warehouse/data/hex_nut_with_flange_parameters.csv
bd_warehouse/data/imperial_set_screw_parameters.csv
bd_warehouse/data/internal_tooth_lock_washer_parameters.csv
bd_warehouse/data/iso10664def.csv
bd_warehouse/data/low_profile_parameters.csv
bd_warehouse/data/metric_set_screw_parameters.csv
bd_warehouse/data/nominal_screw_lengths.csv
bd_warehouse/data/pan_head_parameters.csv
bd_warehouse/data/pan_head_with_collar_parameters.csv
bd_warehouse/data/plain_washer_parameters.csv
bd_warehouse/data/raised_cheese_head_parameters.csv
bd_warehouse/data/raised_countersunk_oval_head_parameters.csv
bd_warehouse/data/setscrew_parameters.csv
bd_warehouse/data/single_row_angular_contact_ball_bearing_parameters.csv
bd_warehouse/data/single_row_capped_deep_groove_ball_bearing_parameters.csv
bd_warehouse/data/single_row_cylindrical_roller_bearing_parameters.csv
bd_warehouse/data/single_row_deep_groove_ball_bearing_parameters.csv
bd_warehouse/data/single_row_tapered_roller_bearing_parameters.csv
bd_warehouse/data/socket_head_cap_parameters.csv
bd_warehouse/data/square_nut_parameters.csv
bd_warehouse-0.1.1.dist-info/licenses/LICENSE
bd_warehouse-0.1.1.dist-info/METADATA
bd_warehouse-0.1.1.dist-info/WHEEL
bd_warehouse-0.1.1.dist-info/top_level.txt
bd_warehouse-0.1.1.dist-info/RECORD
