Metadata-Version: 2.4
Name: bd_warehouse
Version: 0.1.1
Summary: A build123d parametric part collection
Author-email: Roger Maitland <gumyr9@gmail.com>
License: Apache-2.0
Keywords: 3d models,3d printing,3d,brep,cad,cadquery,opencascade,python
Classifier: License :: OSI Approved :: Apache Software License
Classifier: Operating System :: OS Independent
Classifier: Programming Language :: Python :: 3
Requires-Python: <3.14,>=3.10
License-File: LICENSE
Requires-Dist: build123d>=0.10.0
Requires-Dist: typing_extensions<5,>=4.4.0
Provides-Extra: docs
Requires-Dist: sphinx==8.1.3; extra == "docs"
Requires-Dist: sphinx-design; extra == "docs"
Requires-Dist: sphinx-copybutton; extra == "docs"
Requires-Dist: sphinx-hoverxref; extra == "docs"
Requires-Dist: sphinx-rtd-theme; extra == "docs"
Requires-Dist: sphinx-autodoc-typehints; extra == "docs"
Provides-Extra: development
Requires-Dist: black; extra == "development"
Requires-Dist: mypy; extra == "development"
Requires-Dist: pytest; extra == "development"
Requires-Dist: pytest-cov; extra == "development"
Requires-Dist: wheel; extra == "development"
Provides-Extra: all
Requires-Dist: bd_warehouse[docs]; extra == "all"
Requires-Dist: bd_warehouse[development]; extra == "all"
Dynamic: license-file
